ensemblify/__init__.py
ensemblify/clash_checking.py
ensemblify/cli.py
ensemblify/config.py
ensemblify/analysis/__init__.py
ensemblify/analysis/colors.py
ensemblify/analysis/data.py
ensemblify/analysis/figures.py
ensemblify/analysis/rama_ref_data.npy
ensemblify/analysis/trajectory.py
ensemblify/analysis/third_party/THIRD_PARTY_NOTICE_mdreader.txt
ensemblify/analysis/third_party/simple_mdreader.py
ensemblify/analysis/third_party/mdreader-master/.gitignore
ensemblify/analysis/third_party/mdreader-master/LICENSE
ensemblify/analysis/third_party/mdreader-master/__init__.py
ensemblify/analysis/third_party/mdreader-master/mdreader.py
ensemblify/analysis/third_party/mdreader-master/examples/AngleWithZ-fixedgroups.py
ensemblify/analysis/third_party/mdreader-master/examples/AngleWithZ-multgroups.py
ensemblify/analysis/third_party/mdreader-master/examples/AngleWithZ-ndxgroups.py
ensemblify/analysis/third_party/mdreader-master/examples/AngleWithZ-ndxgroupsParallel.py
ensemblify/analysis/third_party/mdreader-master/examples/AngleWithZ-ndxgroupsParallel_noargparse.py
ensemblify/analysis/third_party/mdreader-master/examples/AngleWithZ-simplified.py
ensemblify/analysis/third_party/mdreader-master/examples/CoordinatePropExtraction.py
ensemblify/analysis/third_party/mdreader-master/examples/Density.py
ensemblify/analysis/third_party/mdreader-master/examples/SimpleIterator.py
ensemblify/analysis/third_party/mdreader-master/examples/index.ndx
ensemblify/analysis/third_party/mdreader-master/examples/start.gro
ensemblify/analysis/third_party/mdreader-master/examples/traj.xtc
ensemblify/conversion/__init__.py
ensemblify/conversion/conversion_utils.py
ensemblify/conversion/ensemble2trajectory.py
ensemblify/conversion/trajectory2saxs.py
ensemblify/generation/__init__.py
ensemblify/generation/ensemble.py
ensemblify/generation/ensemble_utils/__init__.py
ensemblify/generation/ensemble_utils/functions.py
ensemblify/generation/ensemble_utils/movers.py
ensemblify-1.0.0.dist-info/licenses/LICENSE
ensemblify-1.0.0.dist-info/METADATA
ensemblify-1.0.0.dist-info/WHEEL
ensemblify-1.0.0.dist-info/entry_points.txt
ensemblify-1.0.0.dist-info/top_level.txt
ensemblify-1.0.0.dist-info/RECORD
