Metadata-Version: 2.4
Name: ensemblify
Version: 1.0.0
Summary: A Python package for generating ensembles of intrinsically disordered regions of AlphaFold or user defined models.
Author-email: "Nuno P. Fernandes" <nmpfernandes@itqb.unl.pt>
Project-URL: Repository, https://github.com/npfernandes/ensemblify
Classifier: Development Status :: 3 - Alpha
Classifier: Programming Language :: Python :: 3
Classifier: License :: OSI Approved :: GNU General Public License v3 (GPLv3)
Classifier: Operating System :: POSIX :: Linux
Classifier: Intended Audience :: Science/Research
Classifier: Topic :: Scientific/Engineering :: Bio-Informatics
Requires-Python: >=3.10
License-File: LICENSE
Requires-Dist: biopython==1.81
Requires-Dist: MDAnalysis==2.6.1
Requires-Dist: mdtraj==1.9.9
Requires-Dist: numpy==1.26.4
Requires-Dist: pandas==2.2.2
Requires-Dist: plotly==5.23.0
Requires-Dist: pyarrow==13.0.0
Requires-Dist: pyyaml==6.0.1
Requires-Dist: ray==2.33.0
Requires-Dist: scikit-learn==1.4.2
Requires-Dist: scipy==1.12.0
Requires-Dist: tqdm==4.66.2
Dynamic: license-file
